planesections/__init__.py
planesections/builder.py
planesections/environment.py
planesections/section.py
planesections/analysis/__init__.py
planesections/analysis/openSees.py
planesections/analysis/pynite.py
planesections/analysis/recorder.py
planesections/diagram/__init__.py
planesections/diagram/diagram.py
planesections/diagram/components/__init__.py
planesections/diagram/components/abstract.py
planesections/diagram/components/basic.py
planesections/diagram/components/basic_old.py
planesections/postprocess/__init__.py
planesections/postprocess/parse.py
planesections/postprocess/plot.py
planesections/postprocess/poi.py
planesections/units/__init__.py
planesections/units/diagramUnits.py
planesections/units/metric.py
planesections-1.4.2.dist-info/licenses/LICENSE
planesections-1.4.2.dist-info/METADATA
planesections-1.4.2.dist-info/WHEEL
planesections-1.4.2.dist-info/top_level.txt
planesections-1.4.2.dist-info/RECORD
