Metadata-Version: 2.4
Name: planesections
Version: 1.4.2
Summary: A light-weight FEM beam analyzer.
Author-email: Christian Slotboom <christian.slotboom@gmail.com>
License-Expression: GPL-3.0-only
Project-URL: Homepage, https://github.com/cslotboom/planesections
Project-URL: Documentation, https://planesections.readthedocs.io/en/latest/
Keywords: FEM,structures,beams,diagrams
Classifier: Development Status :: 5 - Production/Stable
Classifier: Intended Audience :: Science/Research
Classifier: Intended Audience :: Developers
Classifier: Programming Language :: Python
Classifier: Programming Language :: Python :: 3
Classifier: Programming Language :: Python :: 3.9
Classifier: Programming Language :: Python :: 3.10
Classifier: Programming Language :: Python :: 3.11
Classifier: Programming Language :: Python :: 3.12
Classifier: Programming Language :: Python :: 3 :: Only
Classifier: Topic :: Software Development
Classifier: Topic :: Scientific/Engineering
Classifier: Operating System :: Microsoft :: Windows
Classifier: Operating System :: POSIX
Classifier: Operating System :: Unix
Classifier: Operating System :: MacOS
Requires-Python: >=3.9
License-File: LICENSE
Requires-Dist: numpy
Requires-Dist: matplotlib
Requires-Dist: PyniteFEA==1.0.1
Requires-Dist: textalloc==1.1.8
Provides-Extra: opensees
Requires-Dist: openseespy; extra == "opensees"
Dynamic: license-file
